MANIFEST.in
README.rst
gprof.py
setup.py
gprof.egg-info/PKG-INFO
gprof.egg-info/SOURCES.txt
gprof.egg-info/dependency_links.txt
gprof.egg-info/top_level.txt