Metadata-Version: 1.0
Name: gprof
Version: 1.0.3
Summary: Greenlet profiler. Measures CPU time (instead of wall time) and designed specially for greenlets.
Home-page: https://bitbucket.org/rushman/gprof
Author: Sergey Kirillov
Author-email: sergey.kirillov@gmail.com
License: UNKNOWN
Platform: UNKNOWN
